nonebot_plugin_bili_helper/__init__.py
nonebot_plugin_bili_helper/config.py
nonebot_plugin_bili_helper/handlers/bili_helper.py
nonebot_plugin_bili_helper/modules/api_base.py
nonebot_plugin_bili_helper/modules/bilibili_api_host.py
nonebot_plugin_bili_helper/modules/bilibili_apis.py
nonebot_plugin_bili_helper/modules/bilibili_encoder.py
nonebot_plugin_bili_helper/modules/browser_adapter.py
nonebot_plugin_bili_helper/modules/browser_adapter_playwright.py
nonebot_plugin_bili_helper/modules/bv2av.py
nonebot_plugin_bili_helper/renderer/bilibili_comment.py
nonebot_plugin_bili_helper/resources/font/HarmonyOS_Sans_SC_Regular.woff2
nonebot_plugin_bili_helper/resources/font/bilifont/bilifont.1.woff2
nonebot_plugin_bili_helper/resources/font/bilifont/bilifont.2.woff2
nonebot_plugin_bili_helper/resources/font/bilifont/font.css
nonebot_plugin_bili_helper/resources/font/font.css
nonebot_plugin_bili_helper/resources/image/bilibili/bilibili-dark.png
nonebot_plugin_bili_helper/resources/image/bilibili/bilibili-light.png
nonebot_plugin_bili_helper/resources/image/bilibili/bilibili.png
nonebot_plugin_bili_helper/resources/image/bilibili/id-dark.svg
nonebot_plugin_bili_helper/resources/image/bilibili/id-light.svg
nonebot_plugin_bili_helper/resources/image/bilibili/like-dark.svg
nonebot_plugin_bili_helper/resources/image/bilibili/like-light.svg
nonebot_plugin_bili_helper/resources/image/bilibili/直播中.png
nonebot_plugin_bili_helper/resources/image/pic1.png
nonebot_plugin_bili_helper/resources/libs/template-web.js
nonebot_plugin_bili_helper/resources/mocks/bilibili/comments.json
nonebot_plugin_bili_helper/resources/mocks/bilibili/video_info.json
nonebot_plugin_bili_helper/resources/render/.gitignore
nonebot_plugin_bili_helper/resources/render/@formatters/bilibili.js
nonebot_plugin_bili_helper/resources/render/@libs/renderer-node.js
nonebot_plugin_bili_helper/resources/render/@libs/renderer.js
nonebot_plugin_bili_helper/resources/render/@libs/scripts.js
nonebot_plugin_bili_helper-0.9.3.dist-info/METADATA
nonebot_plugin_bili_helper-0.9.3.dist-info/WHEEL
nonebot_plugin_bili_helper-0.9.3.dist-info/licenses/LICENSE
nonebot_plugin_bili_helper-0.9.3.dist-info/RECORD
