Metadata-Version: 2.4
Name: nonebot_plugin_bili_helper
Version: 0.9.3
Summary: Nonebot2 plugin for bilibili sharing detail
License: MIT
License-File: LICENSE
Author: krimeshu
Author-email: krimeshu@gmail.com
Requires-Python: >=3.9,<4.0
Classifier: License :: OSI Approved :: MIT License
Classifier: Programming Language :: Python :: 3
Classifier: Programming Language :: Python :: 3.9
Classifier: Programming Language :: Python :: 3.10
Classifier: Programming Language :: Python :: 3.11
Classifier: Programming Language :: Python :: 3.12
Classifier: Programming Language :: Python :: 3.13
Classifier: Programming Language :: Python :: 3.14
Requires-Dist: aiohttp (>=3.12.15,<4.0.0)
Requires-Dist: nonebot-adapter-onebot (>=2.0.0,<3.0.0)
Requires-Dist: nonebot-plugin-htmlrender (>=0.6.0,<0.7.0)
Requires-Dist: nonebot-plugin-localstore (>=0.7.4,<0.8.0)
Requires-Dist: nonebot2 (>=2.3.0,<3.0.0)
Project-URL: Homepage, https://github.com/krimeshu/nonebot-plugin-bili-helper
Project-URL: Repository, https://github.com/krimeshu/nonebot-plugin-bili-helper
